{
  "id": "878630",
  "name": "blog",
  "font_family": "iconfont",
  "css_prefix_text": "icon-",
  "description": "",
  "glyphs": [
    {
      "icon_id": "1131937",
      "name": "编辑",
      "font_class": "bianji",
      "unicode": "e635",
      "unicode_decimal": 58933
    },
    {
      "icon_id": "2198901",
      "name": "游戏竞技",
      "font_class": "youxijingji",
      "unicode": "e61a",
      "unicode_decimal": 58906
    },
    {
      "icon_id": "8952924",
      "name": "java-script",
      "font_class": "javascript",
      "unicode": "e810",
      "unicode_decimal": 59408
    },
    {
      "icon_id": "9599344",
      "name": "我的简历",
      "font_class": "wodejianli",
      "unicode": "e67b",
      "unicode_decimal": 59003
    },
    {
      "icon_id": "14441174",
      "name": "plus",
      "font_class": "plus",
      "unicode": "e694",
      "unicode_decimal": 59028
    },
    {
      "icon_id": "774444",
      "name": "扳手",
      "font_class": "zujian",
      "unicode": "e65c",
      "unicode_decimal": 58972
    },
    {
      "icon_id": "1160785",
      "name": "ios-world",
      "font_class": "world",
      "unicode": "e821",
      "unicode_decimal": 59425
    },
    {
      "icon_id": "1210728",
      "name": "事件检测器",
      "font_class": "shijian",
      "unicode": "e7fa",
      "unicode_decimal": 59386
    },
    {
      "icon_id": "5703783",
      "name": "jsx-1",
      "font_class": "jsx",
      "unicode": "e609",
      "unicode_decimal": 58889
    },
    {
      "icon_id": "11231623",
      "name": "loading",
      "font_class": "zhouqi",
      "unicode": "e782",
      "unicode_decimal": 59266
    },
    {
      "icon_id": "15797091",
      "name": "【视图】渲染模式",
      "font_class": "xuanran",
      "unicode": "e656",
      "unicode_decimal": 58966
    },
    {
      "icon_id": "23259593",
      "name": "cryo",
      "font_class": "yuansu",
      "unicode": "e60e",
      "unicode_decimal": 58894
    },
    {
      "icon_id": "5029",
      "name": "列表",
      "font_class": "liebiao",
      "unicode": "e600",
      "unicode_decimal": 58880
    },
    {
      "icon_id": "10594757",
      "name": "表-带图表单_jurassic",
      "font_class": "biaodan",
      "unicode": "e6b0",
      "unicode_decimal": 59056
    }
  ]
}
